[
  {
    "filename": "No_Error_Popup",
    "displayName": "noerror",
    "description": "You dont get the '721' error anymore"
  },
  {
   "filename": "gmiV2_0930.fbmod",
    "displayName": "gmi",
    "description": "Game mode info, usage on own risk"
  },
  {
    "filename": "Auto Voice Mute.fbmod",
    "displayName": "automute",
    "description": "Mute automatically all people in a lobby"
  },
  {
    "filename": "Reysious' Hit SFX.fbmod",
    "displayName": "hitsound",
    "description": "Adds the hit sound effect (Classic COD Hit Marker) from the Reysious' videos"
  },
  {
    "filename": "Reysious' Kill SFX.fbmod",
    "displayName": "killsound",
    "description": "Adds the kill sound effect (Nice Meme) from Reysious' videos"
  }
]